DOCUMENT.txt
MANIFEST.in
README.rst
setup.py
django_tts_reports.egg-info/PKG-INFO
django_tts_reports.egg-info/SOURCES.txt
django_tts_reports.egg-info/dependency_links.txt
django_tts_reports.egg-info/top_level.txt
reports/__init__.py
reports/admin.py
reports/apps.py
reports/models.py
reports/services.py
reports/tests.py
reports/url.py
reports/views.py
reports/migrations/0001_initial.py
reports/migrations/__init__.py
reports/templates/buyer-report.html
reports/templates/deal-buyer-report/Sourcing.html
reports/templates/deal-buyer-report/anaylsis.html
reports/templates/deal-buyer-report/buyers.html
reports/templates/deal-buyer-report/middle-cost.html
reports/templatetags/__init__.py
reports/templatetags/base_extras.py